parqueryd/__init__.py
parqueryd/config.py
parqueryd/controller.py
parqueryd/messages.py
parqueryd/node.py
parqueryd/rpc.py
parqueryd/tool.py
parqueryd/util.py
parqueryd/version.py
parqueryd/worker.py
parqueryd-0.1.33.dist-info/LICENSE
parqueryd-0.1.33.dist-info/METADATA
parqueryd-0.1.33.dist-info/WHEEL
parqueryd-0.1.33.dist-info/entry_points.txt
parqueryd-0.1.33.dist-info/top_level.txt
parqueryd-0.1.33.dist-info/zip-safe
parqueryd-0.1.33.dist-info/RECORD
