Metadata-Version: 2.1
Name: parqueryd
Version: 0.1.33
Summary: A distribution framework for parquery
Home-page: https://github.com/visualfabriq/parqueryd
Author: Carst Vaartjes
Author-email: cvaartjes@visualfabriq.com
Maintainer: Carst Vaartjes
Maintainer-email: cvaartjes@visualfabriq.com
License: GPL2
Platform: any
Classifier: Development Status :: 4 - Beta
Classifier: Intended Audience :: Developers
Classifier: Intended Audience :: Information Technology
Classifier: Intended Audience :: Science/Research
Classifier: License :: OSI Approved :: BSD License
Classifier: Programming Language :: Python
Classifier: Topic :: Software Development :: Libraries :: Python Modules
Classifier: Operating System :: Microsoft :: Windows
Classifier: Operating System :: Unix
Classifier: Programming Language :: Python :: 2
Classifier: Programming Language :: Python :: 2.7
Classifier: Programming Language :: Python :: 3
Classifier: Programming Language :: Python :: 3.5
Classifier: Programming Language :: Python :: 3.6
Classifier: Programming Language :: Python :: 3.7
Classifier: Programming Language :: Python :: 3.8
Classifier: Programming Language :: Python :: 3.9
Requires-Dist: azure-storage-blob (>=12.4.0)
Requires-Dist: boto3 (>=1.14.40)
Requires-Dist: configobj (>=5.0.6)
Requires-Dist: netifaces (>=0.10.9)
Requires-Dist: parquery (>=0.1.15)
Requires-Dist: psutil (>=5.7.2)
Requires-Dist: pyzmq (>=19.0.2)
Requires-Dist: redis (>=3.5.3)
Requires-Dist: smart-open (>=1.11.1)
Provides-Extra: optional
Provides-Extra: test
Requires-Dist: codacy-coverage (>=1.3.11) ; extra == 'test'
Requires-Dist: pytest-cov (>=2.10.0) ; extra == 'test'
Requires-Dist: pytest (>=4.6.11) ; extra == 'test'
